{
  "rss_0_1776020266": {
    "title": "Nigerian airstrike targeting jihadists reportedly kills at least 100 civilians",
    "text": "A Nigerian air force strike targeting jihadist rebels hit a market in north-east Nigeria, killing more than 100 people and injuring many others, Amnesty International and local media have said.\n\nOfficials confirmed a misfire had occurred but did not provide details.\n\nAmnesty International said it confirmed from survivors that at least 100 people had been killed in the airstrike on a village in Yobe state near the border with Borno state, the centre of the jihadist insurgency that has ravaged the region for more than a decade.\n\nThe Nigerian military often conducts air raids to battle armed groups who use vast forest enclaves, and have killed at least 500 civilians since 2017, according to an Associated Press tally of reported deaths.\n\nSecurity analysts have pointed to loopholes in intelligence gathering, as well as insufficient coordination between ground troops, air assets and stakeholders.\n\nThe Yobe state government confirmed in a statement that a Nigerian military strike had targeted a stronghold of the Boko Haram jihadist group in the area and that “some people … who went to the Jilli weekly market were affected.”\n\nIsa Sanusi, Amnesty International’s Nigeria director, said: “We are in touch with people that are there; we spoke with the hospital. We spoke with the person in charge of casualties and we spoke with the victims.”\n\nThe Nigerian air force did not immediately respond to inquiries."
  },
  "rss_1_1776020267": {
    "title": "Mauritius vows to ‘decolonise’ Chagos Islands after Starmer shelves handover",
    "text": "A senior official in Mauritius’ government has vowed that the Chagos Islands will be “decolonised” after Keir Starmer was forced to shelve legislation to hand the islands back to Mauritius.\n\nOn Friday, UK government officials acknowledged that they had run out of time to pass legislation within the current parliamentary session, which ends in the coming weeks, after a lack of support from Donald Trump.\n\nAfter the collapse of the plan to hand the islands over voluntarily, Dhananjay Ramful, the Mauritian foreign minister, told an Indian Ocean conference in Mauritius that his government would regain control over the territory.\n\n“We will spare no effort to seize any diplomatic or legal avenue to complete the decolonisation process,” he said, in comments that were first reported in the Sunday Telegraph. “This is a matter of justice.”\n\nThe latest setback in the UK’s bid to hand the Chagos Islands to Mauritius, which hosts the joint US-UK Diego Garcia military base, is a sign of faltering US-UK relations after Trump’s criticism of Starmer over the war in Iran.\n\nThe US president had criticised the Chagos plan, which is backed by the US state department, telling Starmer he was “making a big mistake” by handing sovereignty of the islands to Mauritius in exchange for the UK and US being allowed to continue using their airbase.\n\nTrump later gave qualified support, but the UK was forced to drop the bill after the US failed to give its approval by formally exchanging letters to amend a 1966 British-American treaty on the islands. A new Chagos bill is not now expected to feature in the king’s speech in May, where the government’s agenda for the coming parliament is revealed.\n\nThe Chagos Islands are officially known as British Indian Ocean Territory and have been controlled by the UK since the 19th century. In 2019, the international court of justice found that the UK unlawfully separated the islands from Mauritius before it granted independence to the country in 1968. Thousands of islanders were then forcibly deported to make way for the US-UK military base.\n\nA government spokesperson said: “Diego Garcia is a key strategic military asset for both the UK and the US. Ensuring its long-term operational security is, and will continue to be, our priority – it is the entire reason for the deal.\n\n“We continue to believe the agreement is the best way to protect the long-term future of the base, but we have always said we would only proceed with the deal if it has US support.”\n\nThe shelved plan, which was agreed with the previous US president Joe Biden, would have seen Britain cede sovereignty of the Chagos to Mauritius and pay about £35bn to lease the airbase back for 99 years.\n\nSimon McDonald, a former permanent under-secretary at the Foreign Office, told BBC Radio 4’s Today programme that the government had “no other choice” than to halt the deal. “When the president of the United States is openly hostile, the government has to rethink, so this agreement, this treaty will go into the deep freeze for the time being,” he said.\n\nThe Mauritius attorney general, Gavin Glover, said the outcome “does not come as a surprise”, blaming it on strained relations between Trump and Starmer, reported Arab News. “We are dependent on Anglo-American relations … the US and Britain will have to reach an agreement,” Glover told a local newspaper. Mauritius is planning to meet the British government on 22 April over the Chagos deal, he said.\n\nOn Sunday, the health secretary, Wes Streeting, denied that the UK’s deal to hand over the Chagos Islands to Mauritius was moribund. “It is fair to say there has been a shift in position in Washington,” he said. “We’ve been clear throughout that the objective is to make sure we secure the Chagos Islands for the long term in British and American interests. I think there are lots of people in the US administration who understand what we’re trying to achieve, who support that objective.”"
  },
  "rss_2_1776020267": {
    "title": "Benin holds presidential election four months after failed coup",
    "text": "This Sunday, just four months after a failed coup, Benin heads to the polls for a presidential election that feels more like a coronation than a contest.\n\nPatrice Talon, the businessman turned politician who has been president since 2016, is ineligible to run again after serving two five-year terms.\n\nThe winner of Sunday’s election will have the chance to run for two seven-year terms instead, after a controversial constitutional amendment elongated presidential tenures.\n\nRomuald Wadagni, the country’s finance minister who emerged as the ruling coalition’s candidate without any primaries, is overwhelmingly the favourite to win this weekend.\n\nAccording to the investigative newsletter Africa Confidential, the path to a Wadagni win was cleared with ruthless efficiency as other possible contenders were sidelined, placated or removed.\n\nWadagni, who speaks English fluently after years as a technocrat in the US, is seen as the architect of Benin’s recent fiscal stability in the Talon era. He has vowed to implement free schooling and more jobs, appealing promises in a country where young people account for more than half of the population.\n\nIf the 49-year-old emerges as the winner, he will be one of the youngest leaders on a continent where the average presidential age is 65. West and central Africa is home to two of the world’s longest-serving leaders in Cameroon’s 93-year-old Paul Biya and Equatorial Guinea’s Teodoro Obiang Nguema, 83.\n\nA peaceful democratic transition after the failed coup also presents Benin an opportunity to buck another regional trend: at least three of its neighbours are ruled by juntas. But Talon’s critics say he is also a strongman in a similar mould and have accused him of crushing dissent despite noticeable development in the country.\n\nView image in fullscreen Patrice Talon arriving to cast his vote at a polling station in Cotonou. Photograph: Olympia de Maismont/AFP/Getty Images\n\nDiscontent trickled down to some troops and coalesced into December’s attempted military takeover. But many believe the soldiers also acted because of a rise in jihadist attacks at its borders with Burkina Faso, Niger and Nigeria.\n\nSeveral newspapers have been closed indefinitely by authorities after publishing information critical of the government. Hugues Sossoukpè, a journalist who had been in exile in Togo since 2021, was arrested on Ivorian soil by Beninese agents last July. He remains in Ouidah prison, tagged as a “dangerous cyberactivist who advocates terrorism”.\n\nView image in fullscreen Patrice Talon, the businessman turned politician who has been president since 2016, is ineligible to run again. Photograph: Benin TV/Reuters TV/Reuters\n\n“Civic space continues to shrink in Benin with a wave of attacks on independent media outlets and people still being arbitrarily arrested and detained for dissent,” said Dieudonné Dagbéto, the head of Amnesty International Benin. “Despite progress, women and marginalised groups face discrimination, while forced evictions jeopardise the human rights of thousands of people.”\n\nThere are also concerns about Benin increasingly becoming a one-party state. In 2024, parliament raised the thresholds for candidacy, now requiring parties to get at least 10% of the vote to secure seats and for an aspiring president to be sponsored by at least 15% of the country’s mayors and lawmakers. That helped the ruling coalition win all 109 seats in January’s legislative elections as opposition parties found it extremely difficult to make the cut.\n\nOnly 36% of the approximately 7.8 million people registered to vote showed up for the January poll. Ahead of this weekend, there are concerns about a similar outcome.\n\nThe main opposition to Wadagni is the former culture minister Paul Hounkpè of Cowry Forces for an Emerging Benin (FCBE), a fringe opposition party. He is seen as a token candidate after cutting a deal with the ruling coalition to meet the required threshold.\n\nUnable to meet the requirements, the lead opposition party, the Democrats, are not presenting any candidates. While they have not called for a boycott, they have refused to back anyone in this weekend’s election. In fact, the party suspended almost two dozen members for anti-party activities after reportedly endorsing the ruling coalition candidate.\n\n“The disqualification of our duo [candidate and running mate] is a programmed exclusion,” it said in a statement after the constitutional court affirmed the exclusion last October. “It proves that the 2026 election is being organised to exclude any serious challenger to the ruling power.”"
  },
  "rss_3_1776020267": {
    "title": "Prince Harry sued for defamation by charity he co-founded",
    "text": "The Duke of Sussex is being sued by Sentebale in the latest twist in the bitter fallout over the African charity he co-founded.\n\nThe charity has lodged papers in London’s high court over defamation claims naming Prince Harry and the former Sentebale trustee Mark Dyer as defendants.\n\nThe prince had been engaged in a public war of words with the charity’s chair, Dr Sophie Chandauka, after his resignation as a patron last year.\n\nSentebale works with children and young people in southern Africa. Harry and the co-founder Prince Seeiso of Lesotho stepped down in March 2025, and trustees later quit over a dispute with Chandauka, a lawyer appointed in 2023.\n\nSentebale said it had begun legal proceedings after “a coordinated adverse media campaign conducted since 25 March 2025 that has caused operational disruption and reputational harm to the charity, its leadership and its strategic partners”.\n\nIt added: “The proceedings have been brought against Prince Harry and Mark Dyer, identified through evidence as the architects of that adverse media campaign, which has had significant viral impact and triggered an onslaught of cyberbullying directed at the charity and its leadership.\n\n“Sentebale has experienced the adverse media campaign as false narratives circulated through the media about the charity and its leadership, attempts to undermine its relationships with staff, existing and prospective partners, and the forced diversion of leadership time and resources into managing a reputational crisis not of the charity’s making.\n\n“The charity should not continue to use its resources to manage and address the damage this adverse media campaign has caused to its operations and partnerships. This must stop. The board and executive director have taken this legal action to secure that protection. The costs of doing so are met entirely by external funding and no charitable funds have been used.”\n\nThe claim was filed on 24 March, according to HM Courts and Tribunals Service, though further details were not available.\n\nA spokesperson for the Duke of Sussex and Mark Dyer said: “As Sentebale’s co-founder and a founding trustee, they categorically reject these offensive and damaging claims.\n\n“It is extraordinary that charitable funds are now being used to pursue legal action against the very people who built and supported the organisation for nearly two decades, rather than being directed to the communities the charity was created to serve.”\n\nIn August 2025, the Charity Commission criticised Harry for allowing a row with the chair to “play out publicly”, while clearing him of racism.\n\nAfter his resignation was made public, Chandauka said she had been targeted by people who “play the victim card”. She described the dispute as a “story of a woman who dared to blow the whistle about issues of poor governance, weak executive management, abuse of power, bullying, harassment, misogyny, misogynoir [discrimination against black women] – and the cover-up that ensued”.\n\nIn its compliance case ruling, the regulator criticised all those involved in the dispute for “allowing it to play out publicly”. It said the then trustees’ failure to resolve disagreements internally had “severely impacted the charity’s reputation and risked undermining public trust in charities more generally”.\n\nThe commission found that a serious dispute between Chandauka and Harry followed the formulation of a new fundraising strategy in the US.\n\nIn response at the time, a spokesperson for Harry – who was not a trustee and established the charity in memory of his mother, Diana, Princess of Wales – criticised the commission, saying its report had fallen “troublingly short”.\n\nThey said: “Unsurprisingly, the commission makes no findings of wrongdoing in relation to Sentebale’s co-founder and former patron, Prince Harry, Duke of Sussex.\n\n“They also found no evidence of widespread bullying, harassment or misogyny and misogynoir at the charity, as falsely claimed by the current chair.\n\n“Despite all that, their report falls troublingly short in many regards, primarily the fact that the consequences of the current chair’s actions will not be borne by her – but by the children who rely on Sentebale’s support.\n\n“Sentebale has been a deeply personal and transformative mission for Prince Harry, established to serve some of the most vulnerable children in Lesotho and Botswana.”"
  },
  "rss_4_1776020267": {
    "title": "Four men deported by US to Eswatini have right to see lawyer, court rules",
    "text": "Four men deported by the US to Eswatini and denied in-person legal counsel for nine months while detained in a maximum security prison have the right to see a local lawyer, Eswatini’s supreme court ruled.\n\nThe men, from Cambodia, Cuba, Vietnam and Yemen, were sent to the small southern African country, formerly known as Swaziland, in July despite having no connection to the country, as part of Donald Trump’s administration’s efforts to ramp up deportations.\n\nThe US government had labelled the men dangerous criminals. Their lawyers said they had already served sentences for crimes committed in the US. Eswatini’s correctional services refused to let a local lawyer see the men, although they allowed them to make calls to their US lawyers, the lawyers said.\n\nThe court rejected the government’s argument that “the inmates persistently showed no interest” in meeting the human rights lawyer Sibusiso Magnificent Nhlabatsi, in a judgment handed down on Thursday.\n\nThe three judges ruled: “There can be no real harm in granting the respondent access to the detainees … it then will be up to the detainees, if they do not wish to see the respondent, to tell this to the respondent to his face.”\n\nOf the first five deportees, one was repatriated to Jamaica in September. Another 10 arrived in Eswatini in October, one of whom was repatriated to Cambodia on 26 March, and a further four last month.\n\nAlma David, a US lawyer for several of the men, said: “The fact that it took nearly nine months of litigation and a decision by the highest court of the land to obtain something as innocuous as permission for my clients to meet with a local lawyer speaks volumes about how hard the government of Eswatini is fighting to deny these men the most basic of rights.”\n\nThe Eswatini government spokesperson, Thabile Mdluli, did not immediately respond to a request for comment. Previously, she has said: “The government of the Kingdom of Eswatini has made every reasonable effort, in accordance with national laws and international obligations, to ensure that the third-country nationals received from the United States government are accommodated in conditions that respect their fundamental rights and human dignity.”\n\nThe US has deported dozens of people to third countries from which they do not originate, including Ghana, South Sudan and Uganda. Human rights lawyers and NGOs have labelled the deportations as a form of human trafficking.\n\nA spokesperson for the US Department of Homeland Security said: “Allegations that sending criminal illegal aliens to third country’s [sic] is a form of ‘human trafficking’ is insane. The Trump administration is utilizing all lawful options to carry out the largest deportation operation in history, just as President Trump promised.”"
  },
  "rss_5_1776020267": {
    "title": "Peruvians go to polls hoping to break cycle of instability",
    "text": "Peruvians go to the polls on Sunday hoping to break a cycle of instability that has produced nine presidents in a decade as well as surging violent crime, corruption scandals and overwhelming distrust in institutions and politicians.\n\nAbout 27 million people who are eligible to vote must choose between a record 35 presidential candidates as well as contenders for the bicameral congress – all from a ballot sheet measuring nearly half a metre, the longest in the country’s history.\n\nThe fight against crime tops voter concerns amid record homicide and extortion rates but political corruption comes a close second. Four former presidents are in jail, most of them linked to bribery cases involving the Brazilian construction company Odebrecht.\n\nKeiko Fujimori, a three-time presidential candidate and the daughter of the late president Alberto Fujimori, holds a narrow lead in opinion polls. She is closely followed by the comedian Carlos Álvarez and two former mayors of Lima, the ultra-conservative Rafael López Aliaga and the media mogul Ricardo Belmont.\n\nView image in fullscreen Keiko Fujimori, daughter of the late president Alberto Fujimori , holds a narrow lead in the opinion polls.\n\nNone of the candidates is polling above 15%, making a runoff on 7 June almost certain, according to Urpi Torrado, of the polling company Datum Internacional.\n\n“This is one of the most unpredictable elections on record,” said Torrado. “There could be surprises this Sunday because we don’t know who will make it through to the second round.”\n\nFujimori, 50, is making her fourth bid for the presidency, having reached the runoff in the last three elections (2021, 2016 and 2011) and losing by extremely narrow margins each time. The rightwinger served as first lady in the autocratic 1990s government of her late father, who was convicted over corruption and human rights abuses and spent 16 years in prison.\n\nRicardo Belmont, who was Lima’s mayor from 1990 to 1995, has risen in most opinion polls, winning the younger vote with his upbeat messaging and the slogan “hugs not bullets”, borrowed from the former Mexican leader Andrés Manuel López Obrador.\n\nGonzalo Banda, a Peruvian political analyst and doctoral researcher at University College of London’s Institute of the Americas, called Belmont an “anti-establishment candidate catching votes from the right, the left and the centre”. The 80-year-old is also known for making xenophobic and sexist remarks.\n\nView image in fullscreen A band plays in support of Jorge Nieto, a former Peruvian defence minister, at a rally in Lima on Thursday. Photograph: Sebastián Blanco/EPA\n\nLópez Aliaga, who was Lima’s mayor until a few months ago, has run a hard-right campaign littered with disinformation, hate speech and threats against journalists and opponents. But the 65-year-old rail magnate, who has opposed same-sex marriage and pledged to refuse abortion to underage rape victims, has slipped in the polls.\n\nThe surprise entry is Álvarez, one of Peru’s best-known comedians, who has been imitating presidents for the last three decades. However, his proposals are far from lighthearted. He describes himself as an admirer of Donald Trump and El Salvador’s leader, Nayib Bukele, and his tough-on-crime campaign has focused on megaprisons and the death penalty.\n\n“It is ironically poetic that due to this cycle of [political] decay in Peru, we could end up with a comedy performer who imitates politicians as president,” said Banda.\n\nOther candidates include Roberto Sánchez, who has been endorsed by the ousted former populist leader Pedro Castillo and wears the same style of wide-brimmed sombrero. Centrist candidates include a former defence minister, Jorge Nieto, and a former university rector, Alfonso López Chau.\n\nTorrado said: “No political leader has emerged who can generate a sense of hope, a feeling that this person could change the country’s political course or solve its problems. Peruvians feel that in recent years, politicians have turned their backs on the people.”"
  },
  "rss_6_1776020268": {
    "title": "At least 30 killed in crush at historic fortress in Haiti",
    "text": "At least 30 people, many of them young, have died and dozens more are reported to have been injured after a crush at a mountaintop fortress in northern Haiti that is a popular tourist spot.\n\nJean Henri Petit, the head of civil protection for the country’s Nord department, said the incident took place on Saturday at Citadelle Henry, also known as Citadelle Laferrière, a large 19th-century fortress built shortly after the Caribbean country’s independence from France.\n\nHe told the local newspaper Le Nouvelliste that the death toll could rise due to the large number of people reported missing. Several dozen people were taken to hospital, the outlet reported.\n\nInitial reports said visitors were crammed against a single entrance and a scuffle broke out between those trying to leave and enter the site.\n\nOther local media reports said a gathering took place after being advertised on TikTok. There were also reports of rumours that police at the site used too much teargas to break up a fight near the citadel, which caused people to panic and triggered a crush.\n\nThe country’s culture minister, Emmanuel Menard, confirmed that 30 people had died. He said: “The injured are currently receiving the necessary medical care, and a rescue team is searching for any missing persons.”\n\nMenard said the fortress, which was listed as a Unesco world heritage site in 1982, would remain closed to visitors until further notice.\n\nHaiti’s prime minister’s office expressed “deep sadness”, in a government statement posted on Facebook, and said the crush occurred during “a tourist activity bringing together many young people”.\n\nThe government urged citizens to “be calm and cautious” while it investigated. “All competent authorities are fully mobilised and placed on maximum alert to provide, without delay, the necessary assistance, care and support,” it added in its statement.\n\nThe crush comes as Haiti continues to grapple with widespread violence by gangs that have massacred civilians, as well as an increasingly deadly crackdown by security forces.\n\nHaiti, the poorest country in the western hemisphere, has also been badly hit by rising oil prices caused by the conflict in Iran. On 2 April, the government announced a 37% increase in the cost of diesel and a 29% increase in the cost of gasoline.\n\nThe surge in oil prices has disrupted critical supply chains, doubled transportation costs and forced millions of undernourished people to cut back on already scarce meals.\n\nThe country has experienced various disasters in recent years, including a 2024 fuel tank explosion that killed two dozen people, another fuel tank blast in 2021 that killed 90 people, and an earthquake that left about 2,000 people dead that same year.\n\nReuters, Associated Press and Agence France-Presse contributed to this report"
  },
  "rss_7_1776020268": {
    "title": "US man in Bahamian jail after wife disappears into Atlantic waters during boat trip",
    "text": "Lynette Hooker bounced around the deck of the docked Soul Mate, smiled into the camera and proclaimed, “We’re finally leaving Kemah,” referring to a Texas port town.\n\n“It’s only been four months,” she said as her husband, Brian, tugged on some rigging as they got ready to set sail.\n\nThe Gulf Crossing video in 2023 marked the start of a sailing adventure – chronicled on Facebook – for a couple who are now at the center of criminal investigations after Lynette went missing in the Bahamas.\n\nA few days after Lynette disappeared, police from the Atlantic Ocean island nation arrested Brian.\n\nHe denies any wrongdoing in his wife’s disappearance and has been cooperating with law enforcement, his attorney, Terrel Butler, said.\n\nButler added that Brian Hooker would remain in custody until at least Monday evening while investigators continued examining the case. He told police that his wife of more than 20 years fell overboard on Saturday night from a small motorboat that was carrying the couple from Hope Town to Elbow Cay, small islands on the eastern end of the Bahamas.\n\nHe said Lynette, 55, had the keys to the boat’s engine, which shut off.\n\n“Strong currents subsequently carried her away, and he lost sight of her,” police said in a statement on Saturday.\n\nHe paddled to shore and alerted others early Sunday, said authorities, who arrested and questioned him on Wednesday.\n\nThe US Coast Guard has opened an investigation separate from the one by the Bahamas authorities.\n\nKarli Aylesworth, Lynette’s daughter, has said it’s unlikely her mother would “just fall” from a boat.\n\nAnd while the couple is seen smiling, laughing and joking in social media videos of their voyage, they have a history of contention.\n\nBrian and Lynette Hooker accused each other of assault in 2015, according to a Kentwood, Michigan, police report obtained by NBC News.\n\nBrian Hooker, who was intoxicated and bleeding from the nose, told police his wife had struck him multiple times in the face, the report said. He told officers Lynette also was drunk. She was arrested for assault and spent the night in jail. A warrant was denied because it wasn’t clear “who started the assault”.\n\nAylesworth also told NBC that the couple’s relationship was volatile and that they have a “history of not getting along, especially when they drink”.\n\nThe couple’s home is in Onsted, about 72 miles (117 km) south-west of Detroit. The closest big body of water is Lake Erie, about 60 miles (72km) south-east of Onsted.\n\nLynette Hooker’s mother, Darlene Hamlett, said on Wednesday that the family “grew up on water” and that her daughter’s life has been “near lakes, on boats, sailing and swimming”.\n\nThe couple posted videos of their years sailing around the Caribbean on their Facebook page named Sailing Hookers.\n\nLynette, in the March 2023 Gulf Crossing video, describes the start of the couple’s voyage aboard the Soul Mate as the sailboat slips through the Kemah, Texas, fog and into the open waters of the Gulf of Mexico.\n\n“Pretty cool,” Lynette said as Brian blared the Soul Mate’s foghorn. Later, while changing an engine alternator belt, he looks up at his wife and says, “Hi, sexy.”\n\nIn an earlier video, the couple explains how they bought the Soul Mate in the coastal town of Rockport, Texas, and fixed it up.\n\n“After several years of driving around the country, looking for our perfect sailboat, we finally found her in Texas,” Lynette said in that eight-minute video, posted in January 2023. “She was a little rough on the edges. The decks needed to be redone, but we knew we were up for the task.”\n\nThat video shows them working together, scraping, priming and painting. “The decks are done! We’re still married! Party time!” is printed in a message on the video.\n\nA video posted in 2024 shows them using their smaller motorboat to buy food on land. The video doesn’t give the couple’s location.\n\n“We got the grub,” Brian says into the camera, which shifts to a case of beer at his feet and bags of groceries in the bow. “Delivery … the way of life, man.”"
  },
  "rss_8_1776020268": {
    "title": "Human rights groups decry US plan for Guantánamo camp for Cuban migrants",
    "text": "Dozens of US and international human rights organizations are decrying the Trump administration’s plans to establish a migrant “camp” for fleeing Cubans at the Guantánamo Bay military base if the island nation’s crisis worsens under pressure from the US, according to a letter to members of Congress on Friday.\n\nThe 85 groups plan to submit the joint letter, exclusively shared with the Guardian, to US senators and House representatives, expressing their “profound concern” with comments made last month by a top Department of Defense commander, and describing any prospect of further migrant detention at the base as “deeply troubling and unacceptable”.\n\nThe commander told Congress last month that in the event of what one Republican senator described as “any humanitarian crisis” in Cuba, the Pentagon would “set up a camp” at the Guantánamo Bay US base to “deal with” migrants.\n\nThe United Nations already warned in February that Cuba could be on the brink of a humanitarian “collapse” following Donald Trump’s attempts to block oil supplies from reaching the island and the US president repeatedly threatening Cuba’s communist government.\n\n“Guantánamo should be a relic of the past,” the organizations’ letter to the lawmakers reads. “We call on you to act without delay to ensure not another dollar goes towards the detention facilities at Guantánamo, ensure the base is never again used for unlawful mass detention of any group of people, and end the coercive and punitive policy of sanctions and the embargo driving the humanitarian crisis.”\n\nThe letter has been signed by groups including the Center for Constitutional Rights, which has represented dozens of detainees held at Guantánamo during America’s so-called war on terror since the 2001 terrorist attacks on the US on September 11. The less well-known migrant detention facilities are separate from the terrorism-related detention center at the base.\n\n“Both have long been known for inhumane conditions, mistreatment, and due process violations,” Friday’s letter states.\n\nOther signatories include a wide variety of US and international advocacy, religious, legal and policy groups such as the Center for Victims of Torture, a chapter of Amnesty International, the Center for Economic and Policy Research, Refugees International, the justice team at Sisters of Mercy of the Americas, the Council on American-Islamic Relations, Detention Watch Network and more.\n\n“Guantánamo stands alone in its reputation as the most heinous and dangerous place the US president can possibly send you – outside view, under the radar, beyond the law,” said Yumna Rizvi, a senior policy analyst for the Center for Victims of Torture. “The US can provide immediate relief to the Cuban people, but instead is choosing to cause irreparable harm and then double down by threatening detention at Guantánamo for Cubans who need to flee because of his own actions. It is outrageous.”\n\nDuring a US Senate armed services committee hearing on 19 March, Gen Francis Donovan, the commander of US Southern Command (Southcom), which oversees the Guantánamo Bay base on a tiny portion of US-claimed land on Cuba, testified it could be used to establish a new version of a migrant “camp” for Cubans.\n\nWhen asked by the Republican senator Tom Cotton of Arkansas about military preparations in response to any humanitarian crisis in Cuba, Donovan said that Southcom was under orders to “support DHS [the Department of Homeland Security] in a mass migration event”.\n\n“We would follow either at sea, or primarily the shore, primarily at Guantánamo Bay, to set up a camp to deal with those migrants or any overflow from any situation in Cuba itself,” Donovan said.\n\nIn a radical escalation of immigration enforcement early last year, Trump signed an executive order to expand migrant detention operations at Guantánamo and began sending immigrants from the US to be held there, often en route to deportation. About 780 immigrants detained in the US have been sent to Guantánamo since last February, sometimes for weeks at a time, according to a tally by the New York Times.\n\nThe Migrant Operations Center (MOC) is a facility at Guantánamo under the purview of both the Pentagon and the DHS and has been used for decades to detain a small number of migrants interdicted at sea.\n\nThe Guardian revealed last year that the private US government contractor running the MOC has fallen under scrutiny for conditions inside other immigration jails it operates. In addition to using the MOC, the administration began to quickly put up tents in a costly and controversial plan to detain an estimated 30,000 migrants at Guantánamo amid the second Trump administration’s focus on a harsh anti-immigration agenda. But the tents were never used and the installations were dismantled.\n\nAfter the January abduction of the Venezuelan president, Nicolás Maduro, the Trump administration turned its attention on Cuba. “Cuba is next, by the way,” Trump said in March.\n\n“If the Trump administration is worried about Cuban migration, the solution is simple: stop intentionally impoverishing the Cuban people through an embargo and fuel blockade,” said Michael Galant, a senior research and outreach associate with the Center for Economic and Policy Research, one of the groups that signed on to Friday’s letter."
  },
  "rss_9_1776020268": {
    "title": "Trump ‘reaping bitter fruit’ of thinking Iran intervention as easy as Venezuela, says former diplomat",
    "text": "Donald Trump is “reaping the bitter fruit” of erroneously thinking that the capture of Venezuela’s president, Nicolás Maduro, offered a blueprint for toppling the Iranian regime, according to one of the US state department’s most respected former Latin America experts.\n\nJohn Feeley, a Marine helicopter pilot who later served as the US ambassador to Panama, believed Trump had been “flush with the victory from Venezuela” when he made the ill-fated decision to attack Iran in February, leaving a trail of destruction across the Middle East and dealing a hammer blow to the global economy.\n\nMaduro was seized during a special forces mission on 3 January, with the remnants of his authoritarian regime quickly capitulating to US demands under the leadership of his replacement, Delcy Rodríguez. More than 100 Cuban and Venezuelan troops lost their lives during Trump’s Operation Absolute Resolve but not a single member of the US military was killed.\n\n“This was one of the most stunning, effective, and powerful displays of American military might and competence in American history,” Trump boasted last month, calling his attack proof the US had “the strongest and most fearsome military on the planet”.\n\nView image in fullscreen John Feeley (seen here in 2010 speaking in Mexico City as the US deputy chief of mission) voiced fears a similar miscalculation might soon be made in Cuba. Photograph: Eliana Aponte/Reuters\n\nFeeley accepted Maduro’s capture had shown Trump’s administration was “willing to use force to get rid of somebody they don’t like”. But he and other former senior US diplomats believed it had also lulled the US president into the false belief that removing Iran’s supreme leader, Ali Khamenei, and his regime would be as straightforward as overthrowing the South American autocrat.\n\n“We are now literally reaping the bitter fruit of a decision made in large [part] to go into Iran based on the unbelievable good luck that he had in Venezuela,” said Feeley, emphasising that his comments were not a criticism of the elite forces who snatched Maduro.\n\n“As somebody who flew in those units … I can’t tell you how many things could have gone horribly wrong,” he said of the night-time raid involving Delta Force commandos and members of an elite aviation unit known as the Night Stalkers.\n\nFeeley, who left the foreign service during Trump’s first term, said the Venezuela assault had led Trump to expect a similarly “marvellous little two-week, three-ribbon war” in Iran. “I think it’s very true that the success of the Venezuela episode led him to give the green light … and begin the Iran episode,” he said, voicing fears that a similar miscalculation might soon be made in Cuba, which Trump recently vowed to “take”.\n\n“I think these guys will make the very jejune and naive mistake of thinking that Cuba is going to be just like Venezuela, in the same way they misunderstood that Iran was going to be just like Venezuela,” he said.\n\n“These are 70-year regimes, 50-year regimes in the case of Iran. They’re decentralised, the ranks are trained, they’ve been indoctrinated … That’s a very different scenario than Venezuela, which was a criminal mafia that had only really consolidated its position in the last decade. But I think this administration is shortsighted enough … to still foolishly believe: ‘We’ll just go in there’.”\n\nView image in fullscreen ‘In many ways, Venezuela becomes the wrong example,’ said Thomas Shannon, a former US ambassador to Brazil and responsible for Latin America policy in the George W Bush administration. Photograph: Juan Barreto/AFP/Getty Images\n\nThomas Shannon, a Venezuela specialist and former ambassador to Brazil who was responsible for Latin America policy under George W Bush, was also convinced Trump’s Venezuela intervention had caused him to make a grave miscalculation in the Middle East.\n\n“He actually thought Iran was going to be the same thing. I mean, [Trump] knew that they couldn’t sweep in and arrest the supreme leader. But he thought they could go in and kill him and that they could kill any number of other leaders, both civil and military, and that that display would have the same impact the raid on Caracas had,” said Shannon, who believed Trump had hoped to replace Iran’s ayatollah with a compliant, Rodríguez-style figure. No such leader has emerged.\n\nShannon said: “In many ways, Venezuela becomes the wrong example. But it’s the one that the president has in mind when he decides to join the Israelis in the 28 February attack. The problem is that the circumstances are quite different and the Iranians are different. And they have a resilience and a kind of internal capacity and structures to endure these kinds of assaults without having to surrender or to pretend to surrender.”\n\nFeeley saw an irony to how, by yielding to Trump’s January attack, the US president’s longtime foes in Caracas had inadvertently lured the US into making such a damaging misjudgment more than 7,000 miles away in Tehran.\n\n“Obviously, hard power is hard power and there’s nothing that they could do to prevent Trump doing what he did [in Venezuela],” Feeley said. “But their ultimate revenge is that they kind of laid down and made it look easy – and so [Trump] thought: ‘Oh, I’ll try that in an ancient Persian empire, a millennial civilisation. Threaten to blow the whole civilisation up.’ And we are where we are.”"
  }
}