{
  "rss_0_1782763480": {
    "title": "‘Everyone is talking about Cape Verde’: World Cup run delights diaspora community in UK",
    "text": "For as long as she can remember, 13-year-old Lauryn struggled to find a map that included Cape Verde. Now, to her great delight, the tiny African island nation is finally centre stage.\n\n“Seeing our country shown across the world at the World Cup makes me feel incredibly proud,” Lauryn says. “After the first match, everyone was talking about Cape Verde. People saw the talent and the skill of our players.”\n\nCape Verde, or Cabo Verde as the diaspora community in the UK knows it, are having a historic run at their first ever World Cup. The African nation, made up of 10 islands, has defied expectations by holding its own against the tournament’s leading teams.\n\nLocated in the Atlantic Ocean about 370 miles (600km) off the coast of mainland Africa, and with a population of just over 500,000, it is one of the smallest nations to compete at the tournament.\n\nLauryn, who has already published her first book, Lauryn That’s Me: The Journey of a Powerful African Girl, says she scrolled through social media before Cape Verde’s opening match against Spain. “There were lots of posts on social media saying Cape Verde only had a 1% chance of winning. But after everyone saw our goalkeeper’s performance, everything changed.”\n\nView image in fullscreen Goalkeeper Vozinha celebrates after Cape Verde’s draw with Uruguay. Photograph: Xinhua/Shutterstock\n\nThat 1% prediction has since become a rallying cry for the Cape Verdean diaspora in Britain, which is estimated to number in the low thousands. “Our slogan in the Cape Verdean community became: ‘They gave us 1% chance, but we had 99% faith,’” Lauryn says.\n\nThe team held a stunned Spain to a 0-0 draw. Their next match, against Uruguay, felt like a “constant heart attack”, says Annabella Lopes of the Cape Verdean Association UK. The game ended 2-2.\n\nNow, the team, quickly becoming fans’ favourite underdogs, face Saudi Arabia in their final group stage match, which kicks off at 9pm ET on Friday in Houston, Texas – or 1am Saturday for Lauryn and others watching in the UK. A win will secure them a historic spot in the knockouts, while a draw will give them a fighting chance to qualify as one of the eight best third-placed teams.\n\nLauryn’s younger brother, 10-year-old Joylen, who plays football for Chelsea’s academy, says watching the tournament has strengthened his belief in the team. “I think we can definitely go very far. I knew people shouldn’t underestimate us because if we can draw against Spain and Uruguay, imagine what we can do against other teams.”\n\nIt has also inspired his own ambition. “It makes me want to reach my highest level,” he says.\n\nFor Lopes, the team’s performance sends a powerful message to the Cape Verde diaspora community across the world, as well as those who hail from small countries. “The success happening on the pitch reflects the resilience and strength of our people,” she says. “The fact that you are small, and the fact that people don’t know you, doesn’t mean you can’t achieve great things.”\n\nskip past newsletter promotion Free newsletter | Every weekday Sign up to First Edition Our morning email breaks down the key stories of the day, telling you what’s happening and why it matters Preview latest Enter your email Sign up after newsletter promotion\n\nView image in fullscreen Cape Verde supporters in Rotterdam in the Netherlands. Photograph: Robin Utrecht/EPA\n\nShe adds that it is not about winning or losing. “The important thing is to take part. Cape Verde is taking part, Cape Verde is competing, Cape Verde is achieving, and Cape Verde is making history.”\n\nMuch of the admiration has centred on the veteran goalkeeper Vozinha, whose Instagram page went from hundreds of thousands to nearly 10 million followers over the space of two games.\n\nNancy Rodrigues, a 38-year-old NHS physiotherapist living in the UK, says she treated the “really nice” goalkeeper when living in Angola. “He definitely deserves all the attention he’s getting now,” she says. “It’s amazing because everyone knows Cape Verde through him. That feels incredible.”\n\nElisangela, a 36-year-old accountant, known as Ely, says the team’s success has electrified the diaspora community across the world. “We have never experienced a moment like this before. Everyone is excited. People are calling each other, checking in and asking how they’re feeling and how they’re living through this moment with their families and friends.”\n\nLauryn and Joylen’s mother, Cristina, hopes the team’s success leads to interest in the country that goes much further than football. “We are creative people. There is so much talent, not only in football but also in music, literature and the arts.”\n\nShe says she is particularly proud of the values and resilience the team is showing on the world stage, and points to the Cape Verde manager, Bubista, and his tradition of giving a gift to the coach of the opposing team before the start of each game.\n\n“That’s part of who we are. We come as warriors on the pitch, but we honour and respect one another,” she says. “I think that’s what people are seeing. They’re not seeing arrogance. They’re seeing humility, unity and men crying because they care so much. It’s beautiful.”"
  },
  "rss_1_1782763481": {
    "title": "Whereabouts of nearly 300 people with Ebola unknown in DR Congo",
    "text": "The whereabouts of almost 300 people who have tested positive for Ebola in the Democratic Republic of the Congo is unknown, according to Africa’s top public health official.\n\nThe humanitarian crisis amid the conflict in the affected areas means more than 1 million people are living in camps to which health workers have no access, Dr Jean Kaseya, director general of the Africa Centers for Disease Control and Prevention (CDC), said on Thursday.\n\nHis comments came as projections from the World Health Organization’s Africa regional office, published in the Lancet Infectious Diseases journal, predicted there will be about 8,210 cases and 1,420 deaths by mid-September.\n\nView image in fullscreen Dz’na Lipe Jean‑Marie, secretary of Kpangba displacement camp in the DRC, holds an Ebola awareness session on 13 June 2026. Photograph: Gradel Muyisa Mumbere/Reuters\n\nThe modelling suggested the outbreak had a 70% chance of spreading to neighbouring South Sudan in the coming weeks.\n\nThere have been 1,118 confirmed cases and 291 deaths to date in the DRC, as well as 20 cases and two deaths in neighbouring Uganda.\n\nOn Wednesday, France announced that a doctor who had been working in the DRC had tested positive on his return. His employer, medical NGO Alima, said they were “working to understand how the contamination may have occurred”.\n\nFigures on the number of patients who have recovered and those being treated, as well as deaths, indicate 297 people who tested positive are unaccounted for.\n\n“This is a concern that we have. Where are these people?” asked Kaseya.\n\nDRC authorities said on Thursday that anyone who had been in affected provinces would need to wait 21 days before they could travel onwards.\n\nThe outbreak, caused by the Bundibugyo strain of the virus, is the largest on record for five weeks after declaration. At the same stage, the west Africa outbreak of 2014 to 2016, which infected more than 28,000 people and killed more than 11,000, had 239 cases and 160 deaths.\n\nComputer models were used by the WHO to simulate three trajectories – low, central or high transmissibility.\n\nThere are signs that the DRC’s response is working to slow transmission, the authors said, and current figures are most in line with the central scenario, predicting between 6,636 and 10,287 cases by 16 September.\n\nThe worst-case scenario projects 66,000 confirmed cases by September.\n\nKaseya said 30% of new cases are among known contacts of confirmed cases, indicating “huge, huge community transmission”. Authorities intend to recruit 20,000 community health workers from the local area to boost contact tracing efforts, he said.\n\nBed occupancy in Ebola treatment centres is at 95% and “we didn’t reach the peak yet”, he added.\n\nHe said camps in which displaced people were living “have cases, and because we don’t have access to these camps, we cannot have the contact tracing. We cannot have a photo of what’s happening there. We cannot stop this outbreak, without resolving the humanitarian issue.”\n\nAfrica CDC and the WHO had earlier said $518m (£392m) of health spending would be needed to tackle the outbreak. When humanitarian needs are added, the total rises to $1.4bn, Kaseya said.\n\nOnly about 13% of $910m pledged to the response by international governments and organisations has so far been supplied, he said.\n\nThe first trial of drugs that may be able to treat the Bundibugyo virus is due to begin in the DRC next week, while a trial of an antiviral given to contacts to prevent them developing the disease will begin a week later."
  },
  "rss_2_1782763481": {
    "title": "Outrage as woman jailed for three years after criticising Somali government online",
    "text": "A rickshaw driver in Somalia has been sentenced to three years in prison for comments she made on social media, in a case that has caught the public’s attention and provoked outrage in the country.\n\nSadia Moalim Ali, a 27-year-old nursing graduate, was originally charged with insulting government institutions and incitement to commit a crime, but convicted only of the former. Her sentence, immediately condemned as “fundamentally unjust”, was handed down on 25 June.\n\nShe had made critical comments on Facebook and TikTok about the federal government of Somalia, speaking out about the youth unemployment and high fuel prices gripping the country, as well as against alleged corruption, nepotism and forced evictions.\n\nThe sentencing of the young mother has been condemned by former high-ranking government officials, including the former president of Somalia, Sharif Sheikh Ahmed, and human rights organisations.\n\nHassan Ali Khaire, former prime minister of Somalia, wrote on X: “The three-year prison sentence handed down today … is deeply troubling and fundamentally unjust. This politically motivated arrest and conviction … reflects a disturbing pattern of judicial overreach, political retaliation, and abuse of state authority.”\n\nIn a statement, the Coalition of Somali Human Rights Defenders called for her immediate release, saying: “Ali’s conviction and harsh sentence represent a serious attack on freedom of expression and the legitimate work of human rights defenders in Somalia.”\n\nIt said her case reflected a broader pattern of systematic discrimination against women who advocated for social and political change. “Female human rights defenders in Somalia continue to face disproportionate risks,” it said, “including arbitrary arrest, judicial harassment, intimidation, online abuse and gender-based discrimination, aimed at excluding them from civic and political participation.”\n\nSomali media reported that Mohamed Sheikh Osman, one of Ali’s lawyers, rejected the ruling and said the defence would appeal.\n\n“[Ali] is not satisfied with the decision of the Banaadir Regional Court,” he told reporters. “The court issued a harsh ruling that could have been avoided.”\n\nAli, who is the main breadwinner for her family and has a one-year-old daughter, has been in custody since 12 April. In an interview from prison in May, she told the Guardian she had been subjected to torture. She said: “I was forced to lie face down on the ground, and water was poured on me. I was kicked by guards with boots on. They stood over me and beat me with a baton.\n\n“I was taken into solitary confinement and kept there for two days. I was deprived of food and basic necessities while I was locked in that cell. I wasn’t allowed to leave to go to the toilet.”\n\nAt court, Ali said police officers had threatened her with rape.\n\nTorture – defined as any act by which severe pain or suffering, physical or mental, is intentionally inflicted – is prohibited under international law and by the UN Convention against Torture in all circumstances.\n\nSince 2022, Somali authorities have been accused of engaging in a systematic and escalating crackdown on human rights, using arbitrary arrests, detention, harassment, threats and intimidation to silence journalists, activists and other people who express dissenting views."
  },
  "rss_3_1782763481": {
    "title": "‘Constitutional coup’ claims as Zimbabwe senate approves extending presidential term",
    "text": "Zimbabwe is on the brink of amending its constitution to give the president more time in office, a change that the government says will bring stability but that opponents have labelled a “constitutional coup”.\n\nThe upper house of Zimbabwe’s parliament voted on Wednesday 75-4 in favour of the constitutional amendments, which will allow President Emmerson Mnangagwa to stay in office until 2030 by extending presidential terms from five to seven years.\n\nThe bill, which will also replace direct presidential elections with the appointment of the president by parliament, was passed by the lower house last week and the government said the president was expected to sign it into law next month.\n\nOpposition figures fear the changes could further tighten the hold on power of Mnangagwa, known as “the Crocodile”, and his Zanu-PF party, which has ruled Zimbabwe since independence in 1980.\n\nMnangagwa, now 83, won a second term in office with 52.6% of the vote in the 2023 presidential election, amid criticism of the election process from international observers and opposition figures.\n\nCritics of the constitutional changes claimed Zimbabwe could slide back to the repression seen under Robert Mugabe, who resigned in 2017 after 37 years in power, after a coup led by Mnangagwa.\n\nMakomborero Haruzivishe, a spokesperson for the Constitutional Defenders Forum (CDF), a group campaigning against the amendments, said: “It is a calculated constitutional coup against the people of Zimbabwe. It strips citizens of the fundamental right to directly elect their president, replacing popular sovereignty with parliamentary selection by a captured legislature.”\n\nNick Mangwana, the permanent secretary in Zimbabwe’s information ministry, said: “To characterise this legitimate legislative exercise as a ‘coup’ is not only factually incorrect but deeply disrespectful to the sovereign parliamentary processes of the Republic of Zimbabwe.”\n\nHe said: “The primary objective is to enhance political stability and ensure policy continuity … We are not removing presidential term limits, we are simply adjusting the electoral cycle to reduce the frequency of highly contested, polarising elections.”\n\nMangwana rejected suggestions that constitutional amendments had to be approved in a referendum, saying the attorney general had found no legal basis for requiring a people’s vote.\n\nView image in fullscreen Robert Mugabe addresses party members and supporters gathered at his party headquarters in 2017. Photograph: Jekesai Njikizana/AFP/Getty Images\n\nOpponents of the constitutional amendments said they had been subjected to harassment and prevented from campaigning. Tendai Biti, one of the CDF’s convenors, said security forces had barged into his office six times since October 2025.\n\nResponding to a claim that Biti’s driver had been assaulted in one such incident in March, police said officers had been sent to Biti’s office “for the maintenance of law and order”.\n\nAlso in March, Lovemore Madhuku, a lawyer who had filed a constitutional court challenge to the amendment bill, said he was beaten by a group of balaclava-wearing men who then drove off in unmarked vehicles followed by two police vehicles. Local media published photos of Madhuku with large welts across his upper back.\n\nZimbabwe’s police force said in a statement: “The police were not involved in the alleged incident.”\n\nMangwana said: “If any individual – whether Professor Madhuku, Mr Biti, or anyone else – possesses credible evidence of assault or harassment by state agents, my office urges them to formally lodge a complaint with the [police] or the relevant judicial authorities.”\n\nMangwana said a consultation process had received 537,000 submissions, with an “overwhelming majority supporting the constitutional changes”.\n\nJameson Timba, a minister during Zimbabwe’s government of national unity from 2009 to 2013, said he and his allies had been prevented from speaking during the public consultation events.\n\nTimba said: “We are just the tip of the iceberg. In almost every district that [the government] went to, people were being denied an opportunity to speak … Those public hearings are not a representation of anything. They are a fraud.”\n\nZimbabwe became internationally isolated during the 2000s after Mugabe’s government confiscated more than 4,000 farms from mostly white farmers. Economic output plunged, resulting in hyperinflation in 2008, after which Mugabe was pressed into a coalition government with the opposition at the time.\n\nMany Zimbabweans view Mnangagwa’s rule as a continuation of Mugabe’s. In 2024, the US imposed sanctions on Mnangagwa, his wife, Auxillia, and nine other people, accusing them of corruption."
  },
  "rss_4_1782763481": {
    "title": "France confirms first Ebola case in doctor who had worked in DRC",
    "text": "The first case of Ebola has been confirmed in France, the country’s health ministry has said, in a doctor who had returned from a humanitarian mission to an area affected by the outbreak in the Democratic Republic of the Congo.\n\nThe patient was transferred to a specialist facility and was in a stable condition, the ministry said in a statement. “All precautionary measures, including the patient’s isolation, were taken upon his arrival in the country, with transfer to the hospital under secure conditions to prevent any risk of contamination.”\n\nAuthorities are tracing the patient’s contacts, who will have to isolate at home for 21 days. The ministry said the risk to the general European public was very low.\n\nThe outbreak is centred on Ituri province in north-eastern DRC, where authorities are battling to contain the spread of the virus.\n\nThere had been 1,048 confirmed cases and 267 deaths as of 21 June, according to the DRC health ministry’s latest data, while 112 people have recovered. Neighbouring Uganda has recorded 20 cases and two deaths.\n\nThe World Health Organization declared the outbreak on 15 May, and two days later declared a public health emergency of international concern. Experts believe the virus was circulating in the DRC undetected for weeks before, however, and that the scale of the outbreak there is likely to be much larger than the confirmed cases suggest.\n\nView image in fullscreen Medical workers disinfect themselves at an Ebola treatment centre in Mongbwalu, in Ituri province, DRC. Photograph: Xinhua/Shutterstock\n\nThe humanitarian response has been complicated by aid cuts and conflict in North and South Kivu provinces, to the south of Ituri, where the Rwanda-backed M23 rebel group operates and Ebola cases have also been detected.\n\nThe outbreak had the largest number of confirmed cases within the first month of any Ebola outbreak, the WHO official Abdirahman Mahamud said on Tuesday.\n\nMahamud said local resistance to the response in DRC, which had included hospitals and treatment centres being burned down, was waning. “More and more communities are aware of the risk of Ebola and are asking for tools to support and ​protect themselves,” he said.\n\nThe current strain of the disease is the rare Bundibugyo virus, which has no vaccine or approved treatment.\n\nModelling by the US Centers for Disease Control and Prevention suggested the outbreak could be the biggest on record. The previous largest outbreak was in west Africa from 2014 to 2016, during which more than 28,000 people were infected and more than 11,000 died.\n\nskip past newsletter promotion Free newsletter | Weekly Sign up to This is Europe The most pressing stories and debates for Europeans – from identity to economics to the environment Preview latest Enter your email Sign up after newsletter promotion\n\nIt is the DRC’s 17th outbreak of Ebola, which was first detected in the central African country in 1976. Scientists believe it spreads to humans from infected African fruit bats, and is then passed between humans through direct contact with the blood or body fluids of an infected person or someone who has died of the disease.\n\nInitial symptoms include fever, exhaustion, muscle pain, headaches and a sore throat. These may progress to vomiting, diarrhoea, abdominal pain, a rash, and impaired kidney and liver function.\n\nA ‌US citizen who was ​treated for ​Ebola in Germany recovered and was discharged earlier this month having tested negative for the virus after 30 May.\n\nThe US government wants to build an Ebola quarantine facility for its citizens in Kenya, which has never recorded any Ebola cases. The country’s health minister said on Tuesday that construction of the highly controversial facility would stop, however, after a high court order that authorities had initially disregarded.\n\nReuters contributed to this report\n\n\n\n"
  },
  "rss_5_1782763481": {
    "title": "Strong aftershock terrifies Venezuelans days after devastating twin quakes",
    "text": "A strong aftershock has rattled northern Venezuela, sending terrified residents racing on to the streets five days after the twin earthquakes that killed 1,719 people, left tens of thousands missing and triggered a growing humanitarian emergency.\n\nThe aftershock early on Monday – which the US Geological Survey measured at a magnitude of 4.6 – shook the capital, Caracas, and the devastated port city of La Guaira, where rescue crews are still hoping to pull as many survivors as possible from the rubble. Colombia’s geological survey put the aftershock’s magnitude at 5.1.\n\nAlthough Jorge Rodríguez, the leader of the Venezuelan national assembly, said there were no immediate reports of new damage, the trembling earth and sounding of quake sirens brought fresh panic to Caracas and La Guaira.\n\n“I was asleep when the shaking woke me up. It felt almost as strong as Wednesday’s earthquake, even though I hadn’t felt the other aftershocks,” said Amarelis Mendoza, a resident of El Hatillo in Caracas.\n\nIn the hardest-hit areas of the capital – including Altamira and San Bernardino – people poured on to the streets from the makeshift shelters where they had been staying. Many have been sleeping outside apartment buildings or in tents pitched along sidewalks, fearing further collapses.\n\nSeveral lines of the Caracas metro were shut down again over concerns that additional aftershocks could further damage already weakened infrastructure.\n\nIn San Bernardino, search operations at the 22-unit Rita apartment building, which collapsed completely during last week’s earthquake, were suspended for about an hour and a half following Monday’s tremor.\n\nAs the new week began, some businesses across the capital started to reopen. But the number of people seeking refuge in parks and public squares continues to grow as the humanitarian crisis deepens.\n\nHundreds of displaced families from Caracas and beyond have been camping out in Parque del Este, a 200-acre park in the east of the capital.\n\n“Life is worth more than anything else,” said 35-year-old Katiuska Asuaje, who fled her home in the La Cruz sector of Bello Campo in Caracas with four children.\n\n“We weren’t going to wait for the house to collapse on top of us because one of the concrete roof slabs had already come loose.”\n\nMaryuri Pérez, 36, and Jaime Blanco, 40, had nowhere to go back to after their shack in west Caracas collapsed.\n\n“What we need most is a tent or at least a mattress to sleep on,” said Pérez. “Thank God the neighbours have been bringing us food, but we have nowhere to sleep.”\n\nThe aftershock came as local people and Venezuelan and international search teams continued to comb the rubble for survivors of last Wednesday’s back-to-back quakes, which measured magnitude 7.2 and 7.5.\n\nThe rescue of a man and his teenage son who were pulled alive from the rubble in La Guaira state on Sunday offered a brief moment of optimism.\n\n“Today we have rescued people who are still alive and therefore these efforts will not be suspended,” said Venezuela’s interim president, Delcy Rodríguez.\n\nBut the chances of similar rescues are dwindling. A Salvadoran rescue worker, who declined to give his name, told Agence France-Presse: “At this point, they are probably dead bodies. Thanks to God maybe we can find people still alive.”\n\nAccording to the government, which has been criticised for its slow response and lack of preparation for the disaster, 5,034 people were injured and almost 800 buildings were badly damaged when the quakes hit.\n\nTens of thousands of people are still missing well after the closure of the critical 72-hour window for rescuing trapped victims following a natural disaster, while millions more lack sanitation and other basic necessities.\n\nEven as rescue efforts continued, outbreaks of looting hit La Guaira, which is near the country’s main international airport. Much of the city now lies in rubble after last week’s disaster. Pharmacies, supermarkets and other businesses were ransacked, said residents, some of whom complained of the slow and meagre post-quake aid coming from authorities.\n\nView image in fullscreen The remains of buildings in El Junquito, Venezuela on Monday. Photograph: Federico Parra/AFP/Getty Images\n\nView image in fullscreen El Junquito on Monday. Photograph: Federico Parra/AFP/Getty Images\n\nThe authorities have barred international journalists from entering the collapse zones in La Guaira for 48 hours, saying the restriction had been imposed for security reasons.\n\nExasperation has boiled over in some areas where people claim that authorities have not done enough to rescue earthquake victims.\n\n“The country needs you. Put down your weapon,” one man shouted to soldiers in the Tanaguarena area of La Guaira state, urging them to swap their guns for picks and shovels.\n\nTwenty-four nations have so far sent 521 tonnes of supplies, 86 units with dogs trained to locate people trapped beneath the rubble and more than 2,700 search-and-rescue personnel, she said.\n\nThe UN migration agency said that up to 6.76 million people could be affected by the disasters, and would require shelter, water, sanitation, healthcare and essential relief items.\n\nVenezuela’s worst earthquakes in more than a century have come after the oil-rich country endured more than a decade of economic collapse. The crisis has hollowed out hospitals and public services, driving millions to leave the country.\n\nThe UN has put the bill for physical repairs at $6.7bn (£5bn) – equivalent to 6% of Venezuela’s GDP. On Monday, the US announced it was doubling its aid package from $150m to $300m.\n\n“These funds will provide emergency medical care, food assistance, water and sanitation, shelter, protection, and logistics,” the state department said.\n\nThe Venezuelan opposition figure María Corina Machado, who is in exile, announced she would return “very soon” to her homeland.\n\n“The time has come,” she told the US broadcaster Fox News on Sunday. “We need to be together, to embrace, to grieve and mourn together, but also to give each other strength at this difficult time.”\n\nAgence France-Presse, the Associated Press and Reuters contributed reporting"
  },
  "rss_6_1782763481": {
    "title": "Venezuela earthquakes aftershock hits near capital city as man rescued from rubble after being trapped for 106 hours – as it happened",
    "text": "From 5h ago 10.12 EDT Rescuers pull 21-year-old man alive from rubble after 106 hours, president says Venezuela’s acting president Delcy Rodríguez has posted footage of the rescuing of Aaron Levi Cantillo Vargas, 21, who she says was trapped under rubble in the town of Caraballeda for 106 hours before being pulled out to safety earlier today (see post at 13.58 for more details). Allow content provided by a third party? This article includes content hosted on platform.x.com . We ask for your permission before anything is loaded, as the provider may be using cookies and other technologies. To view this content, click 'Allow and continue'. Allow and continue Share Updated at 10.31 EDT\n\n2h ago 12.56 EDT Closing summary The United States has pledged more than $300m in funding to aid earthquake-hit Venezuela, the state department said today, up from a previous commitment of $150m. “These funds will provide emergency medical care, food assistance, water and sanitation, shelter, protection, and logistics,” the department said in a statement.\n\nVenezuela’s acting president Delcy Rodríguez has posted footage of the rescuing of Aaron Levi Cantillo Vargas, 21 , who she says was trapped under rubble in the town of Caraballeda for 106 hours before being pulled out to safety earlier today\n\nThe president of Venezuela’s National Assembly has warned time is running out to rescue survivors trapped under the rubble. The death toll from the earthquakes has risen to at least 1,450 people, with 3,150 injured and 12,721 others displaced, Jorge Rodríguez said yesterday in a televised address.\n\nA 4.6-magnitude aftershock centred ⁠at ⁠a depth ​of 10km (six ⁠miles) hit north of the Venezuelan ⁠capital Caracas ​early ‌on ‌Monday, according to ‌the US Geological Survey. No damage was immediately reported from the ‌aftershock.\n\nUS Marines are working to repair the Venezuelan port of La Guaira, a senior administration official said Monday, as Washington boosted its financial commitment for the earthquake-hit country to $300m. A “specialised team of Marines” are “working around the clock to repair that port and allow the delivery of critical supplies by sea,” the US official told journalists on condition of anonymity, adding that the USS Fort Lauderdale – an amphibious transport dock warship – had also docked there.\n\nDilan Yeşilgöz-Zegerius, the Netherlands defence minister and deputy prime minister, said last night that the patrol vessel HNLMS Groningen was heading from the Caribbean to Venezuela to provide assistance to Venezuela following the earthquakes. In a post on X, she said the ship, which will deliver relief supplies, can provide and produce drinking water to affected areas in the country.\n\nThe wife and two children of Argentine footballer Lucas Trejo have died after the powerful twin earthquakes struck Venezuela last week, his team said on Sunday. Trejo, who plays for Club Sport Maritimo La Guaira, a second-division team in Venezuela, had searched for his wife Yanina and children Aarón and Ainhoa in the rubble for three days before rescue workers recovered their bodies, CNN reported.\n\nChina says it will send 100 million yuan ($14.7m; £11.1m) in disaster relief aid to Venezuela. The Chinese government will provide Venezuela with “emergency free relief supplies... to support earthquake relief and post-disaster reconstruction”, foreign ministry spokesperson Guo Jiakun told reporters this morning.\n\nAll schools in Venezuela will remain closed until at least 6 June due to the extensive damage caused by the earthquakes that struck last week, the country’s education ministry has said. The government has urged families to follow official channels to keep informed about the latest developments. Share\n\n3h ago 12.21 EDT Workers remove a large piece of debris as part of the search and rescue efforts at the collapsed residential building Rita, in the San Bernardino neighbourhood. View image in fullscreen Workers set up a chain for crane to remove a large piece of debris as part of the search and rescue efforts at the collapsed residential building Rita in the San Bernardino neighborhood after a magnitude 7.2 earthquake struck Venezuela. Photograph: Edilzon Gamez/Getty Images Share\n\n3h ago 11.39 EDT US Marines are working to repair the Venezuelan port of La Guaira, a senior administration official said Monday, as Washington boosted its financial commitment for the earthquake-hit country to $300m. A “specialised team of Marines” are “working around the clock to repair that port and allow the delivery of critical supplies by sea,” the US official told journalists on condition of anonymity, adding that the USS Fort Lauderdale – an amphibious transport dock warship – had also docked there. La Guaira, on Venezuelan’s northern coast, is one of the country’s two main ports. Share Updated at 12.28 EDT\n\n4h ago 11.11 EDT A residential complex once touted as part of former strongman leader Hugo Chavez’s flagship housing program has been left uninhabitable in Venezuela’s earthquake disaster. Built as part of efforts to modernise Venezuela, the buildings now symbolise the country’s dire situation after twin quakes on Wednesday left nearly 1,500 people confirmed dead and tens of thousands missing. “Most of the buildings at the back of the complex have completely collapsed,” Jenny Contreras, 28, said. Contreras, her husband and their four-year-old son have slept on a mattress in the street since the quakes tore into 192 buildings in the Urbanismo Hugo Chavez complex in the Catia La Mar neighbourhood of La Guaira. The 3,400 apartments have been evacuated and Contreras said she was not even able to return to recover belongings. Large cracks rippled through the buildings, revealing interior construction materials, AFP reporters said. Some were teetering on the verge of collapse and others had already fallen. Even for buildings that are still standing, the future is bleak. “The entire development will be condemned. The whole development is going to disappear in the future because all of it is in very bad condition,” Contreras said. Share\n\n4h ago 10.45 EDT The United States has pledged more than $300m in funding to aid earthquake-hit Venezuela, the state department said today, up from a previous commitment of $150m. “These funds will provide emergency medical care, food assistance, water and sanitation, shelter, protection, and logistics,” the department said in a statement. The money is being directed through partner organisations including Samaritan’s Purse, Catholic Relief Services, the International Organization for Migration, the World Food Programme and the Red Cross, the statement said. Washington has also deployed four urban search-and-rescue teams to Venezuela that are made up of more than 300 first responders and almost two dozen search dogs, the statement added. Share\n\n5h ago 10.16 EDT In a separate post on X, Delcy Rodríguez, who has been criticised for the sluggish official response to the earthquakes, praised the international contribution to the ongoing rescue and relief efforts. She said: double quotation mark We visited the García Carneiro Stadium, where response teams from the international community are located, having arrived to provide support. 30 countries, 3,681 rescuers, 1,086 tons of supplies, 27 vehicles, and 118 canines that bolster the search and rescue efforts. Thank you! Share\n\n5h ago 10.12 EDT Rescuers pull 21-year-old man alive from rubble after 106 hours, president says Venezuela’s acting president Delcy Rodríguez has posted footage of the rescuing of Aaron Levi Cantillo Vargas, 21, who she says was trapped under rubble in the town of Caraballeda for 106 hours before being pulled out to safety earlier today (see post at 13.58 for more details). Allow content provided by a third party? This article includes content hosted on platform.x.com . We ask for your permission before anything is loaded, as the provider may be using cookies and other technologies. To view this content, click 'Allow and continue'. Allow and continue Share Updated at 10.31 EDT\n\n5h ago 09.50 EDT Dilan Yeşilgöz-Zegerius, the Netherland’s defence minister and deputy prime minister, said last night that the patrol vessel HNLMS Groningen was heading from the Caribbean to Venezuela to provide assistance to Venezuela following the earthquakes. In a post on X, she said the ship, which will deliver relief supplies, can provide and produce drinking water to affected areas in the country. Share\n\n6h ago 09.10 EDT The Reuters news agency is reporting that an explosion at a ⁠rig operated by ⁠state-run ​oil company PDVSA ⁠in Venezuela’s Apure state left at ⁠least eight ​workers ‌injured ‌yesterday evening. They were transported to ‌Colombia for medical assistance, according ​to the sources, who spoke under the condition of anonymity. Share"
  },
  "rss_7_1782763482": {
    "title": "Families of two football players killed and injured in Venezuela earthquakes",
    "text": "Family members of two professional footballers are among those killed by the twin earthquakes that struck Venezuela in a catastrophe that has claimed at least 1,719 lives.\n\nAmong the reported victims are the wife and two children of Lucas Trejo, an Argentinian footballer signed to Club Sport Marítimo of La Guaira. He searched through rubble in the coastal city for his wife, Yanina, and their children, Aaron and Ainhoa, for three days before their bodies were recovered by rescue workers.\n\nView image in fullscreen A rescue dog from an Argentinian search and rescue team searches for bodies in the rubble of a collapsed building in Caraballeda, Venezuela, on Sunday. Photograph: Miguel Medina/AFP/Getty Images\n\nTrejo was training with his team in Caracas when the 7.2- and 7.5-magnitude earthquakes struck last Wednesday, CNN reports. He immediately returned to La Guaira, which is in the region worst affected by the earthquake, but “absolutely nothing” was left of his home, according to his brother-in-law, Ricardo Ardiles.\n\nAnother local player, Héctor Bello, lost his wife, Andrea, who died shielding their infant daughter when their home collapsed. The child, Alana, was later found by rescuers, local media reported. She is in a stable condition alongside her aunt, according to Bello, who was away from home when the earthquake struck.\n\n“You gave your own life for our daughter … you were a brave woman who never abandoned her, even as you took your last breaths,” he wrote in an Instagram post.\n\nView image in fullscreen Rescuers use heavy lifting gear to try to uncover earthquake survivors in Caracas, the capital of Venezuela. Photograph: Jimmy Villalta/Zuma Press Wire/Shutterstock\n\nAccording to Venezuelan football officials, the disaster also claimed the lives of youth players Victor Palacios and Razan Sijaa. Palacios played for Club Sport San Augustín’s academy. Sijaa was playing for Caracas Fútbol Club and died with his family at their La Guaira home.\n\nThe 72-hour window where the probability of finding survivors is highest passed on Saturday, according to Sebastian Eugster, leader of the Swiss rescue team. The US Geological Survey predicts deaths could reach 10,000. The earthquake was the most powerful in Venezuela since 1900.\n\nAFP contributed to this report"
  },
  "rss_8_1782763483": {
    "title": "Weather tracker: North-west US hit by snow ahead of eastern heatwave",
    "text": "Unseasonal snow has fallen in some parts of the US, while other parts of the country brace for a heatwave this week.\n\nA strong cold front spread into the western US from the northern Pacific over the weekend, bringing an abrupt change in conditions to a region that had been experiencing high summer temperatures amid drought. Temperatures from the Canadian border to California have widely been 5-10C below the norm since Friday, and more than 10C below in some parts farther north. The pattern is expected to remain for much of the coming week.\n\nThe cold front brought the first significant rainfall in weeks to several parts of the north-west US. Across the Rocky mountains in Idaho, Montana and Wyoming, this combined with the unseasonal cold to produce snowfall at unusually low elevations for the time of year. Whereas the snow line in summer typically sits at about 3,300 metres (11,000ft), snow fell as low as 1,800 metres on Sunday, with more due to fall on Monday. Several inches are expected to accumulate at higher altitudes.\n\nCounterintuitively the cold front has also strongly increased the danger posed by wildfires. With much of the western US currently suffering some form of drought, lightning strikes from the leading edge of the front posed an ignition risk to the widespread dry vegetation and plant litter, while heightened winds fuelled the spread of existing fires.\n\nView image in fullscreen Firefighters watch as the Cottonwood fire burns near Beaver, Utah, on Saturday. Photograph: Noah Berger/AP\n\nThe gustiest conditions over the weekend were in Utah, Colorado, and Arizona, where several major fires were already burning. The strong winds will move north into Wyoming on Monday. The 2026 fire season is shaping up to be one of the worst on record in terms of number and the extent of the areas affected.\n\nTemperatures were a little below average across many other parts of the northern US over the latter part of last week but that is set to radically change over the next few days. A heatwave developing over the north-east in the run-up to the Fourth of July weekend will push temperatures into the high 30s celsius for several parts of the midwest and north-east.\n\nskip past newsletter promotion Free newsletter | Weekly Sign up to Down to Earth The planet's most important stories. Get all the week's environment news - the good, the bad and the essential Preview latest Enter your email Sign up after newsletter promotion\n\nForecast models suggest highs could possibly reach 40C (104F) for cities including New York, Philadelphia and Washington DC on Thursday and Friday, with night-time lows struggling to drop below the high 20s celsius. By contrast, the average daily high for these cities in July varies from 29C in New York to 32C in Washington. The temperature records stand at 42C for New York and 41C for Philadelphia and Washington."
  },
  "rss_9_1782763483": {
    "title": "Venezuela earthquake: father and son found alive in rubble after four days as death toll nears 1,500",
    "text": "A man and his teenage son were found alive under the rubble in Venezuela on Sunday, in a town about 40km north of the capital Caracas, AFP journalists reported, as the death toll from last week’s twin earthquakes passed 1,450.\n\nThe discovery of survivors in Caraballeda was made by French and American rescue teams nearly four days after back-to-back quakes of magnitude 7.2 and 7.5 struck, completely destroying nearly 200 buildings in the area.\n\nInterim president Delcy Rodríguez on Sunday praised rescuers for still pulling survivors from the ruins. “Today we have rescued people who are still alive, and therefore these efforts will not be suspended,” she said. “We always hold on to hope.”\n\nThe rescue offered a glimmer of hope in an ongoing tragedy that has shaken a country already mired in an economic crisis, but tens of thousands of people were still reported missing and the critical 72-hour window for rescuing trapped victims following a natural disaster has now passed.\n\nMillions more people were reported to lack sanitation and other basic needs after one of Latin America’s most devastating earthquake disasters.\n\nView image in fullscreen A rescue worker surveys the rubble in an area affected by the earthquake in Catia La Mar. Photograph: Ronald Pena R/EPA\n\nRescue teams from the US, Mexico and elsewhere scrambled to save people as desperate residents dug by hand for relatives trapped in the pancaked layers and rubble of collapsed apartments.\n\nAbout 774 buildings were badly damaged by the twin quakes that struck on Wednesday evening, National Assembly president Jorge Rodriguez said on Sunday. On Sunday, Rodriguez reported 1,450 dead – a toll expected to rise – with 3,150 people injured.\n\nEven as rescue efforts continued apace, outbreaks of looting hit La Guaira, a port city near the country’s main international airport. Much of the city now lies in rubble after Wednesday’s disaster. Pharmacies, supermarkets and other businesses were ransacked, said residents, some of whom complained of the slow and meagre post-quake aid coming from authorities.\n\nUS helicopters ferried in aid, and 230 more US military personnel were arriving to help expand airport capacity and reopen a key seaport to boost relief efforts, the US Southern Command said on Sunday.\n\nThe US – which seized Venezuela’s former president Nicolás Maduro in a military raid on Caracas in January – had already sent a 250-strong disaster response team.\n\nBut the prospect for rescuing more survivors has dwindled.\n\nA Salvadoran rescue worker who declined to give his name, said: “At this point, they are probably dead bodies. Thanks to God maybe we can find people still alive.”\n\nView image in fullscreen Venezuelan Bolivarian Army soldiers walk in front of a damaged building in La Guaira state. Photograph: Miguel Medina/Reuters\n\nExasperation has boiled over in some locales where residents claim that authorities have not done enough to rescue earthquake victims. “The country needs you. Put down your weapon,” one man shouted to soldiers in the Tanaguarena area of hard-hit La Guaira state, urging them to pick up picks and shovels instead.\n\nFacing public outrage at the response by local officials, President Rodriguez thanked other countries for the outpouring of aid.\n\nTwenty-four nations have sent 521 tons of supplies, 86 units with dogs trained to locate people trapped beneath the rubble and more than 2,700 search-and-rescue personnel, she said.\n\nThe UN migration agency said that up to 6.76 million people could be affected by the disasters, and would require shelter, water, sanitation, healthcare and essential relief items.\n\nVenezuela’s worst earthquakes in more than a century have come after the oil-rich country endured more than a decade of economic collapse. The crisis has hollowed out hospitals and public services, driving millions to leave the country.\n\nThe UN has put the bill for physical repairs at $6.7bn – equivalent to six% of Venezuela’s GDP.\n\nOn Sunday Venezuelan opposition figure Maria Corina Machado, who is in exile, announced she would return “very soon” to her homeland.\n\n“The time has come,” she told US broadcaster Fox News. “We need to be together, to embrace, to grieve and mourn together, but also to give each other strength at this difficult time.”"
  }
}